rail/creation/engines/dsps_photometry_creator.py
rail/creation/engines/dsps_sed_modeler.py
rail/dsps/__init__.py
rail/dsps/_version.py
rail/examples_data/creation_data/data/.DS_Store
rail/examples_data/creation_data/data/dsps_default_data/.DS_Store
rail/examples_data/creation_data/data/dsps_default_data/filters/bass_g_transmission.h5
rail/examples_data/creation_data/data/dsps_default_data/filters/bass_r_transmission.h5
rail/examples_data/creation_data/data/dsps_default_data/filters/lsst_g_transmission.h5
rail/examples_data/creation_data/data/dsps_default_data/filters/lsst_i_transmission.h5
rail/examples_data/creation_data/data/dsps_default_data/filters/lsst_r_transmission.h5
rail/examples_data/creation_data/data/dsps_default_data/filters/lsst_u_transmission.h5
rail/examples_data/creation_data/data/dsps_default_data/filters/lsst_y_transmission.h5
rail/examples_data/creation_data/data/dsps_default_data/filters/lsst_z_transmission.h5
rail/examples_data/creation_data/data/dsps_default_data/filters/mzls_z_transmission.h5
rail/examples_data/creation_data/data/dsps_default_data/filters/suprimecam_b_transmission.h5
rail/examples_data/creation_data/data/dsps_default_data/filters/suprimecam_g_transmission.h5
rail/examples_data/creation_data/data/dsps_default_data/filters/suprimecam_i_transmission.h5
rail/examples_data/creation_data/data/dsps_default_data/filters/suprimecam_r_transmission.h5
rail/examples_data/creation_data/data/dsps_default_data/filters/suprimecam_v_transmission.h5
rail/examples_data/creation_data/data/dsps_default_data/filters/suprimecam_z_transmission.h5
pz_rail_dsps-0.0.3.dist-info/LICENSE
pz_rail_dsps-0.0.3.dist-info/METADATA
pz_rail_dsps-0.0.3.dist-info/WHEEL
pz_rail_dsps-0.0.3.dist-info/top_level.txt
pz_rail_dsps-0.0.3.dist-info/RECORD
