Metadata-Version: 2.1
Name: pz-rail-dsps
Version: 0.0.3
Author-email: "LSST Dark Energy Science Collaboration (DESC)" <later@later.com>
License: MIT License
Classifier: Development Status :: 4 - Beta
Classifier: License :: OSI Approved :: MIT License
Classifier: Intended Audience :: Developers
Classifier: Intended Audience :: Science/Research
Classifier: Operating System :: OS Independent
Classifier: Programming Language :: Python
License-File: LICENSE
Requires-Dist: deprecated
Requires-Dist: pz-rail-base
Requires-Dist: jaxlib
Requires-Dist: dsps
Provides-Extra: dev
Requires-Dist: qp-prob[full] ; extra == 'dev'
Requires-Dist: pytest ; extra == 'dev'
Requires-Dist: pytest-cov ; extra == 'dev'
Requires-Dist: pre-commit ; extra == 'dev'
Requires-Dist: pylint ; extra == 'dev'
